ttmrecganha/__init__.py
ttmrecganha/ttm_model.py
ttmrecganha-0.0.5.dist-info/METADATA
ttmrecganha-0.0.5.dist-info/WHEEL
ttmrecganha-0.0.5.dist-info/top_level.txt
ttmrecganha-0.0.5.dist-info/RECORD
