Metadata-Version: 2.1
Name: ttmrecganha
Version: 0.0.5
Summary: Two Tower Model
Author: acbessa
Author-email: <acbessa@nos.pt>
Classifier: Programming Language :: Python
